loadavgapi-1.1.1.dist-info/DESCRIPTION.rst
loadavgapi-1.1.1.dist-info/METADATA
loadavgapi-1.1.1.dist-info/RECORD
loadavgapi-1.1.1.dist-info/WHEEL
loadavgapi-1.1.1.dist-info/entry_points.txt
loadavgapi-1.1.1.dist-info/metadata.json
loadavgapi-1.1.1.dist-info/top_level.txt
src/__init__.py
src/loadavg.py
